{
  "_fv": 10,
  "_type": "block",
  "definition": {
    "texture": "invisible",
    "textureTop": "invisible",
    "textureLeft": "electricfenceanimated",
    "textureFront": "electricfenceanimated",
    "textureRight": "electricfenceanimated",
    "textureBack": "electricfenceanimated",
    "renderType": 10,
    "customModelName": "Normal",
    "rotationMode": 0,
    "emissiveRendering": true,
    "itemTexture": "",
    "hasTransparency": true,
    "connectedSides": true,
    "transparencyType": "SOLID",
    "mx": 0.0,
    "my": 0.0,
    "mz": 0.0,
    "Mx": 1.0,
    "My": 1.0,
    "Mz": 1.0,
    "name": "Electric Field",
    "specialInfo": [],
    "hardness": 1.0,
    "resistance": 10.0,
    "hasGravity": false,
    "creativeTab": {
      "value": "No creative tab entry"
    },
    "destroyTool": "Not specified",
    "customDrop": {
      "value": ""
    },
    "dropAmount": 1,
    "isBeaconBase": false,
    "enchantPowerBonus": 0.0,
    "plantsGrowOn": false,
    "canProvidePower": false,
    "lightOpacity": 255,
    "material": {
      "value": "AIR"
    },
    "tickRate": 10,
    "tickRandomly": true,
    "isReplaceable": true,
    "colorOnMap": "DEFAULT",
    "creativePickItem": {
      "value": ""
    },
    "offsetType": "NONE",
    "aiPathNodeType": "WALKABLE",
    "flammability": 0,
    "fireSpreadSpeed": 0,
    "isLadder": false,
    "slipperiness": 0.6,
    "reactionToPushing": "IGNORE",
    "isNotColidable": true,
    "soundOnStep": {
      "value": "GLASS"
    },
    "luminance": 0.01,
    "unbreakable": true,
    "breakHarvestLevel": 0,
    "spawnParticles": true,
    "particleToSpawn": {
      "value": "FLASH"
    },
    "particleSpawningShape": "Top",
    "particleSpawningRadious": 0.5,
    "particleAmount": 4,
    "particleCondition": {
      "name": "ElectricFieldParticleSpawningCondition"
    },
    "hasInventory": true,
    "guiBoundTo": "<NONE>",
    "openGUIOnRightClick": false,
    "inventorySize": 1,
    "inventoryStackSize": 64,
    "inventoryDropWhenDestroyed": false,
    "inventoryComparatorPower": false,
    "inventoryOutSlotIDs": [],
    "inventoryInSlotIDs": [],
    "hasEnergyStorage": false,
    "energyInitial": 0,
    "energyCapacity": 400000,
    "energyMaxReceive": 200,
    "energyMaxExtract": 200,
    "isFluidTank": false,
    "fluidCapacity": 8000,
    "fluidRestrictions": [],
    "spawnWorldTypes": [],
    "restrictionBiomes": [],
    "blocksToReplace": [],
    "frequencyPerChunks": 10,
    "frequencyOnChunk": 16,
    "minGenerateHeight": 0,
    "maxGenerateHeight": 64
  }
}